autoqube_kubernetes/__init__.py
autoqube_kubernetes/_version.py
autoqube_kubernetes/aws_kube_cluster_client.py
autoqube_kubernetes/kube_cluster_client.py
autoqube_kubernetes/kubernetes_client.py
autoqube_kubernetes/kubernetes_handler.py
autoqube_kubernetes/load_test_client.py
autoqube_kubernetes/tech_stack_handler.py
autoqube_kubernetes-1.0.2.dist-info/LICENSE
autoqube_kubernetes-1.0.2.dist-info/METADATA
autoqube_kubernetes-1.0.2.dist-info/WHEEL
autoqube_kubernetes-1.0.2.dist-info/top_level.txt
autoqube_kubernetes-1.0.2.dist-info/RECORD
