Metadata-Version: 2.1
Name: autoqube-kubernetes
Version: 1.0.2
Summary: Kubernetes Handler module for AUTOQUBE load testing
Home-page: https://gitlab.com/autoqube/aq-kubernetes
Author: CloudFxLabs
Author-email: gswaroop@cloudfxlabs.io
Maintainer: CloudFxLabs
Maintainer-email: gswaroop@cloudfxlabs.io
License: BSD 3
Keywords: kubernetes jmeter
Platform: UNKNOWN
Requires-Dist: kubernetes
Requires-Dist: pymongo
Requires-Dist: pyyaml
